[
  {
    "JP": "英語でなんて言うか忘れちゃった。",
    "ModelEN": "I forgot how to say it in English."
  },
  {
    "JP": "今その単語が思い出せない。",
    "ModelEN": "I can’t remember the word right now."
  },
  {
    "JP": "この単語が正しいかわからないけど…",
    "ModelEN": "I’m not sure if this is the right word."
  },
  {
    "JP": "これ英語でなんて言うの？",
    "ModelEN": "How do you say this in English?"
  },
  {
    "JP": "おかしいところがあれば直してください。",
    "ModelEN": "Please correct me if anything sounds unnatural."
  },
  {
    "JP": "英語をスラスラと話せるように早くなりたいです。",
    "ModelEN": "I want to get better at speaking English quickly."
  },
  {
    "JP": "私に英語を教えてください。",
    "ModelEN": "Please teach me English."
  },
  {
    "JP": "頑張ります！！",
    "ModelEN": "I’ll do my best!"
  }
]
